canoser/__init__.py
canoser/array_t.py
canoser/base.py
canoser/bool_t.py
canoser/bytes_t.py
canoser/cursor.py
canoser/delegate_t.py
canoser/int_type.py
canoser/map_t.py
canoser/rust_enum.py
canoser/rust_optional.py
canoser/str_t.py
canoser/struct.py
canoser/tuple_t.py
canoser/types.py
canoser/util.py
canoser/version.py
canoser-0.8.2.dist-info/LICENSE
canoser-0.8.2.dist-info/METADATA
canoser-0.8.2.dist-info/WHEEL
canoser-0.8.2.dist-info/top_level.txt
canoser-0.8.2.dist-info/RECORD
