Metadata-Version: 2.1
Name: canoser
Version: 0.8.2
Summary: A python implementation of the LCS(Libra Canonical Serialization) for the Libra network.
Home-page: https://github.com/yuan-xy/canoser-python.git
Author: yuan xinyu
Author-email: yuan_xin_yu@hotmail.com
License: UNKNOWN
Platform: UNKNOWN
Classifier: Programming Language :: Python :: 3
Classifier: License :: OSI Approved :: MIT License
Classifier: Operating System :: OS Independent
Requires-Python: >=3.6
